MANIFEST.in
README.md
setup.cfg
setup.py
bin/add_quality.py
bin/praetor_run.py
praetor2/__init__.py
praetor2/add_quality.py
praetor2/convert2prov.py
praetor2/decorate.py
praetor2/genBindings.py
praetor2/get_import_versions.py
praetor2/praetorTemplates.py
praetor2/praetor_settings.py
praetor2/python_builtin_wrap_templateGen.py
praetor2/python_modules.py
praetor2/templateDictionary.py
praetor2.egg-info/PKG-INFO
praetor2.egg-info/SOURCES.txt
praetor2.egg-info/dependency_links.txt
praetor2.egg-info/not-zip-safe
praetor2.egg-info/requires.txt
praetor2.egg-info/top_level.txt